{
  "default_exchange": "bybit",
  "exchanges": {
    "binance": {
      "name": "Binance",
      "enabled": true,
      "sandbox": true,
      "api_key_env": "BINANCE_API_KEY",
      "api_secret_env": "BINANCE_API_SECRET",
      "rate_limit": 1200,
      "timeout": 30000,
      "fees": {
        "maker": 0.001,
        "taker": 0.001
      },
      "supported_symbols": ["BTC/USDT", "ETH/USDT", "BNB/USDT", "ADA/USDT", "DOT/USDT"],
      "min_order_sizes": {
        "BTC/USDT": 0.00001,
        "ETH/USDT": 0.0001,
        "BNB/USDT": 0.001,
        "ADA/USDT": 1.0,
        "DOT/USDT": 0.1
      }
    },
    "bybit": {
      "name": "Bybit",
      "enabled": false,
      "sandbox": true,
      "api_key_env": "jucNYGEH33v5alHOyI",
      "api_secret_env": "TrzNeE9de4oYHgrzWkSuCGfP0cIPDqSnKZTM",
      "rate_limit": 600,
      "timeout": 30000,
      "fees": {
        "maker": 0.001,
        "taker": 0.001
      },
      "supported_symbols": ["BTC/USDT", "ETH/USDT"],
      "min_order_sizes": {
        "BTC/USDT": 0.00001,
        "ETH/USDT": 0.0001
      }
    },
    "okx": {
      "name": "OKX",
      "enabled": false,
      "sandbox": true,
      "api_key_env": "OKX_API_KEY",
      "api_secret_env": "OKX_API_SECRET",
      "passphrase_env": "OKX_PASSPHRASE",
      "rate_limit": 600,
      "timeout": 30000,
      "fees": {
        "maker": 0.0008,
        "taker": 0.001
      },
      "supported_symbols": ["BTC/USDT", "ETH/USDT"],
      "min_order_sizes": {
        "BTC/USDT": 0.00001,
        "ETH/USDT": 0.0001
      }
    }
  },
  "connection": {
    "max_retries": 3,
    "retry_delay": 1000,
    "heartbeat_interval": 30000,
    "reconnect_on_error": true,
    "use_websocket": true,
    "websocket_timeout": 60000
  },
  "data_collection": {
    "ohlcv_limit": 1000,
    "orderbook_depth": 20,
    "trades_limit": 100,
    "cache_duration_seconds": 300
  },
  "order_management": {
    "default_order_type": "market",
    "allow_market_orders": true,
    "allow_limit_orders": true,
    "allow_stop_orders": true,
    "max_order_age_seconds": 300,
    "cancel_open_orders_on_shutdown": true
  },
  "monitoring": {
    "log_api_calls": true,
    "log_order_updates": true,
    "track_latency": true,
    "alert_on_connection_loss": true,
    "max_acceptable_latency_ms": 1000
  }
}

